yaqd_wright/VERSION
yaqd_wright/__init__.py
yaqd_wright/__version__.py
yaqd_wright/_ndinterp.py
yaqd_wright/_wright_aerotech.py
yaqd_wright/_wright_ingaas.py
yaqd_wright/_wright_stepper_box.py
yaqd_wright/_wright_wl_motor.py
yaqd_wright/ingaas_plot.py
yaqd_wright/ndinterp.avpr
yaqd_wright/ndinterp.toml
yaqd_wright/wright-aerotech.avpr
yaqd_wright/wright-aerotech.toml
yaqd_wright/wright-ingaas.avpr
yaqd_wright/wright-ingaas.toml
yaqd_wright/wright-stepper-box.avpr
yaqd_wright/wright-stepper-box.toml
yaqd_wright/wright-wl-motor.avpr
yaqd_wright/wright-wl-motor.toml
yaqd_wright-2022.8.0.dist-info/entry_points.txt
yaqd_wright-2022.8.0.dist-info/LICENSE
yaqd_wright-2022.8.0.dist-info/WHEEL
yaqd_wright-2022.8.0.dist-info/METADATA
yaqd_wright-2022.8.0.dist-info/RECORD
