Metadata-Version: 2.1
Name: yaqd-wright
Version: 2022.8.0
Summary: yaq daemons for wright group specific hardware, collected together
Home-page: https://yaq.fyi
Author: Wright Group
Author-email: git@ksunden.space
Requires-Python: >=3.7
Classifier: Development Status :: 2 - Pre-Alpha
Classifier: Intended Audience :: Science/Research
Classifier: License :: OSI Approved :: MIT License
Classifier: Natural Language :: English
Classifier: Programming Language :: Python :: 3
Classifier: Programming Language :: Python :: 3.7
Classifier: Programming Language :: Python :: 3.8
Classifier: Topic :: Scientific/Engineering
Requires-Dist: yaqd-core>=2021.3.0
Requires-Dist: pyserial
Requires-Dist: numpy
Requires-Dist: scipy
Requires-Dist: yaqc
Requires-Dist: WrightTools
Requires-Dist: black ; extra == "dev"
Requires-Dist: pre-commit ; extra == "dev"
Project-URL: Issues, https://github.com/wright-group/yaqd-wright/issues
Project-URL: Source, https://github.com/wright-group/yaqd-wright
Provides-Extra: dev
